src/monitoring/__init__.py
src/monitoring/logins/ip_mailer.py
src/rf_survey/Cronify.py
src/rf_survey/GracefulKiller.py
src/rf_survey/Logger.py
src/rf_survey/Restoration.py
src/rf_survey/__init__.py
src/rf_survey/hardware.py
src/rf_survey/kill.py
src/rf_survey/rf_survey.py
src/rf_survey/sweeps.py
src/rf_survey/wr_boot.py
src/rf_survey/wr_poll.py
rf_survey-0.1.dist-info/LICENSE.txt
rf_survey-0.1.dist-info/METADATA
rf_survey-0.1.dist-info/WHEEL
rf_survey-0.1.dist-info/top_level.txt
rf_survey-0.1.dist-info/RECORD
