Metadata-Version: 2.1
Name: rf_survey
Version: 0.1
Summary: An open source tool for measuring baseline radio frequency interference
Author-email: WIRG lab <NSFCUSWIFTPASS@gmail.com>
Project-URL: Homepage, https://github.com/NSFCUSWIFTPASS/RF_survey
Project-URL: Issues, https://github.com/NSFCUSWIFTPASS/RF_survey/issues
Classifier: Programming Language :: Python :: 3
Classifier: License :: OSI Approved :: MIT License
Classifier: Operating System :: OS Independent
Requires-Python: >=3.8
License-File: LICENSE.txt
